tir/__init__.py
tir/cache.py
tir/config.py
tir/deploy.py
tir/files.py
tir/posts.py
tir/server.py
tir/templates.py
tir/tools.py
tir/utils.py
tir/version.py
tir/watch.py
tir/builders/__init__.py
tir/builders/notes.py
tir/cli/__init__.py
tir/parsers/__init__.py
tir/parsers/markdown/__init__.py
tir/parsers/markdown/links.py
tir/parsers/markdown/local_links.py
tir/schemas/__init__.py
tir/schemas/config.py
tir/schemas/deploy.py
tir-0.7.4.dist-info/METADATA
tir-0.7.4.dist-info/WHEEL
tir-0.7.4.dist-info/entry_points.txt
tir-0.7.4.dist-info/licenses/LICENSE.txt
tir-0.7.4.dist-info/RECORD
