Metadata-Version: 2.4
Name: tir
Version: 0.7.4
Summary:  Static site generator for the minimalist 
Author-email: Khalid Ouafi <mail@ouafi.net>
Maintainer-email: Khalid Ouafi <mail@ouafi.net>
License:                     GNU GENERAL PUBLIC LICENSE
License-File: LICENSE.txt
Keywords: blog,site-generator,website
Classifier: Development Status :: 3 - Alpha
Classifier: Intended Audience :: Education
Classifier: License :: OSI Approved :: MIT License
Classifier: Programming Language :: Python :: 3
Classifier: Programming Language :: Python :: 3 :: Only
Classifier: Programming Language :: Python :: 3.9
Classifier: Programming Language :: Python :: 3.10
Classifier: Programming Language :: Python :: 3.11
Classifier: Programming Language :: Python :: 3.12
Classifier: Programming Language :: Python :: 3.13
Classifier: Topic :: Software Development :: Build Tools
Requires-Python: >=3.9
Requires-Dist: csscompressor>=0.9.5
Requires-Dist: jinja2>=3.1.2
Requires-Dist: libsass>=0.21.0
Requires-Dist: markdown>=3.4.4
Requires-Dist: pydantic<3.0.0,>=2.10.6
Requires-Dist: pyyaml>=6.0
Requires-Dist: watchdog<7.0.0,>=6.0.0
Provides-Extra: dev
Requires-Dist: check-manifest; extra == 'dev'
Provides-Extra: test
Requires-Dist: mock>=5.0; extra == 'test'
Requires-Dist: pytest-cov>=4.0; extra == 'test'
Requires-Dist: pytest>=7.0; extra == 'test'
Requires-Dist: tox>=4.0; extra == 'test'
